page/__init__.py
page/_version.py
page/enrichment.py
page/config/default.yaml
page/tests/__init__.py
page/tests/conftest.py
page/tests/test_page.py
page_enrichment-0.1.4.data/data/requirements.test.txt
page_enrichment-0.1.4.data/data/requirements.txt
page_enrichment-0.1.4.dist-info/LICENCE.txt
page_enrichment-0.1.4.dist-info/METADATA
page_enrichment-0.1.4.dist-info/WHEEL
page_enrichment-0.1.4.dist-info/entry_points.txt
page_enrichment-0.1.4.dist-info/top_level.txt
page_enrichment-0.1.4.dist-info/RECORD
