Metadata-Version: 2.1
Name: page-enrichment
Version: 0.1.4
Summary: Parametric Analysis of Gene Set Enrichment (PAGE).
Home-page: https://github.com/afrendeiro/page-enrichment
Author: Andre Rendeiro
Author-email: andre.rendeiro@pm.me
License: GPL3
Project-URL: Bug Tracker, https://github.com/afrendeiro/page-enrichment/issues
Project-URL: Documentation, https://page-enrichment.readthedocs.io
Project-URL: Source Code, https://github.com/afrendeiro/page-enrichment
Keywords: bioinformatics,genetics,enrichement analysis
Platform: UNKNOWN
Classifier: Development Status :: 3 - Alpha
Classifier: License :: OSI Approved :: GNU General Public License v3 or later (GPLv3+)
Classifier: Programming Language :: Python :: 2.7
Classifier: Topic :: Scientific/Engineering :: Bio-Informatics
Requires-Dist: setuptools-scm (>=3.3.3)
Requires-Dist: PyYaml (>=5.2)
Requires-Dist: joblib (>=0.12.5)
Requires-Dist: scipy (>=1.0.0)
Requires-Dist: pandas (>=0.25.0)
Requires-Dist: requests (>=2.21.0)
Provides-Extra: docs
Requires-Dist: sphinx ; extra == 'docs'
Requires-Dist: sphinx-rtd-theme ; extra == 'docs'
Requires-Dist: sphinx-issues ; extra == 'docs'
Requires-Dist: sphinx-argparse ; extra == 'docs'
Provides-Extra: testing
Requires-Dist: pytest (>=4.4.0) ; extra == 'testing'
Requires-Dist: coverage (>=4.5.2) ; extra == 'testing'
Requires-Dist: pytest-cov ; extra == 'testing'
Requires-Dist: codecov ; extra == 'testing'
Requires-Dist: codacy-coverage ; extra == 'testing'
